Metadata-Version: 2.1
Name: bola
Version: 0.2.0
Summary: Collection of sphere packing and meshing algorithms.
Home-page: https://github.com/TTitscher/bola
Author: Thomas Titscher
Author-email: thomas.titscher@gmail.com
License: UNKNOWN
Keywords: molecular-dynamics packing-algorithm gmsh fba edmd
Platform: UNKNOWN
Classifier: Programming Language :: Python :: 3
Classifier: License :: OSI Approved :: MIT License
Classifier: Operating System :: OS Independent
Provides-Extra: dev
Provides-Extra: test
